[
    {
        "changeType": "NEW",
        "changeDescription": "Hypixel Fly"
    },
    {
        "changeType": "FIX",
        "changeDescription": "Fixed Hypixel Scaffold"
    },
    {
        "changeType": "FIX",
        "changeDescription": "Fixed Aura autoblock"
    },
    {
        "changeType": "FIX",
        "changeDescription": "Fix eagle"
    },
    {
        "changeType": "NEW",
        "changeDescription": "BlockAim"
    },
    {
        "changeType": "FIX",
        "changeDescription": "Fix Hypixel title check for chest stealer"
    },
    {
        "changeType": "UPDATE",
        "changeDescription": "Improve Low hop watchdog mode"
    }
]